<?xml version="1.0" encoding="utf-8"?>
<offlineAnnotation>
  <registration>
    <markers>
      <point x="15" y="4" />
      <point x="2901" y="2002" />
    </markers>
    <frameOffset>5</frameOffset>
    <scale>0.0996041885866025</scale>
    <translation>20 9</translation>
    <rotation>0 20 9</rotation>
  </registration>
  <symbols>
    <symbol id="0" name="text">
      <bounds x="1189" y="37" width="225" height="65" />
      <textMeaning>Start</textMeaning>
    </symbol>
    <symbol id="1" name="text">
      <bounds x="639" y="325" width="104" height="43" />
      <textMeaning>No</textMeaning>
    </symbol>
    <symbol id="2" name="text">
      <bounds x="1068" y="292" width="432" height="197" />
      <textMeaning>Do I want\\to do this?</textMeaning>
    </symbol>
    <symbol id="3" name="text">
      <bounds x="1368" y="627" width="104" height="60" />
      <textMeaning>Yes</textMeaning>
    </symbol>
    <symbol id="4" name="text">
      <bounds x="123" y="851" width="455" height="73" />
      <textMeaning>Don't do it.</textMeaning>
    </symbol>
    <symbol id="5" name="text">
      <bounds x="1018" y="822" width="679" height="189" />
      <textMeaning>Will it likely\\end in disaster?</textMeaning>
    </symbol>
    <symbol id="6" name="text">
      <bounds x="1452" y="1235" width="112" height="77" />
      <textMeaning>Yes</textMeaning>
    </symbol>
    <symbol id="7" name="text">
      <bounds x="2771" y="1198" width="99" height="58" />
      <textMeaning>No</textMeaning>
    </symbol>
    <symbol id="8" name="text">
      <bounds x="596" y="1685" width="102" height="39" />
      <textMeaning>No</textMeaning>
    </symbol>
    <symbol id="9" name="text">
      <bounds x="994" y="1560" width="937" height="236" />
      <textMeaning>Will it make a good\\story anyway?</textMeaning>
    </symbol>
    <symbol id="10" name="text">
      <bounds x="2260" y="1586" width="94" height="59" />
      <textMeaning>Yes</textMeaning>
    </symbol>
    <symbol id="11" name="text">
      <bounds x="2531" y="1591" width="284" height="77" />
      <textMeaning>Do it!</textMeaning>
    </symbol>
    <symbol id="12" name="arrow">
      <bounds x="1262" y="141" width="34" height="73" />
      <arrowAnnotation>
        <headBounds x="12467" y="1726" width="337" height="324" />
        <from x="1271" y="141" />
        <to x="1278" y="213" />
      </arrowAnnotation>
    </symbol>
    <symbol id="13" name="arrow">
      <bounds x="286" y="396" width="698" height="400" />
      <arrowAnnotation>
        <headBounds x="286" y="751" width="49" height="45" />
        <from x="983" y="411" />
        <to x="316" y="795" />
      </arrowAnnotation>
    </symbol>
    <symbol id="14" name="arrow">
      <bounds x="1273" y="617" width="51" height="82" />
      <arrowAnnotation>
        <headBounds x="1273" y="663" width="51" height="36" />
        <from x="1294" y="617" />
        <to x="1312" y="699" />
      </arrowAnnotation>
    </symbol>
    <symbol id="15" name="arrow">
      <bounds x="292" y="971" width="535" height="777" />
      <arrowAnnotation>
        <headBounds x="292" y="974" width="56" height="50" />
        <from x="827" y="1729" />
        <to x="315" y="972" />
      </arrowAnnotation>
    </symbol>
    <symbol id="16" name="arrow">
      <bounds x="1373" y="1183" width="73" height="185" />
      <arrowAnnotation>
        <headBounds x="1390" y="1327" width="56" height="42" />
        <from x="1373" y="1183" />
        <to x="1417" y="1368" />
      </arrowAnnotation>
    </symbol>
    <symbol id="17" name="arrow">
      <bounds x="1895" y="874" width="815" height="686" />
      <arrowAnnotation>
        <headBounds x="2645" y="1516" width="64" height="45" />
        <from x="1895" y="874" />
        <to x="2676" y="1559" />
      </arrowAnnotation>
    </symbol>
    <symbol id="18" name="arrow">
      <bounds x="2163" y="1649" width="290" height="50" />
      <arrowAnnotation>
        <headBounds x="2415" y="1649" width="37" height="50" />
        <from x="2163" y="1676" />
        <to x="2452" y="1673" />
      </arrowAnnotation>
    </symbol>
    <symbol id="19" name="decision">
      <bounds x="974" y="205" width="712" height="410" />
    </symbol>
    <symbol id="20" name="decision">
      <bounds x="896" y="692" width="1006" height="511" />
    </symbol>
    <symbol id="21" name="decision">
      <bounds x="828" y="1359" width="1300" height="639" />
    </symbol>
    <symbol id="22" name="terminator">
      <bounds x="1094" y="9" width="390" height="150" />
    </symbol>
    <symbol id="23" name="terminator">
      <bounds x="20" y="811" width="617" height="166" />
    </symbol>
    <symbol id="24" name="terminator">
      <bounds x="2462" y="1563" width="434" height="170" />
    </symbol>
  </symbols>
  <relations>
    <relation id="0" arity="3" name="arrow_connection">
      <symbolView symbolDataRef="12" />
      <symbolView symbolDataRef="22" connectionPoint="bottom" />
      <symbolView symbolDataRef="19" connectionPoint="top" />
    </relation>
    <relation id="1" arity="3" name="arrow_connection">
      <symbolView symbolDataRef="13" />
      <symbolView symbolDataRef="19" connectionPoint="left" />
      <symbolView symbolDataRef="23" connectionPoint="top" />
    </relation>
    <relation id="2" arity="3" name="arrow_connection">
      <symbolView symbolDataRef="14" />
      <symbolView symbolDataRef="19" connectionPoint="bottom" />
      <symbolView symbolDataRef="20" connectionPoint="top" />
    </relation>
    <relation id="3" arity="3" name="arrow_connection">
      <symbolView symbolDataRef="15" />
      <symbolView symbolDataRef="21" connectionPoint="left" />
      <symbolView symbolDataRef="23" connectionPoint="bottom" />
    </relation>
    <relation id="4" arity="3" name="arrow_connection">
      <symbolView symbolDataRef="16" />
      <symbolView symbolDataRef="20" connectionPoint="bottom" />
      <symbolView symbolDataRef="21" connectionPoint="top" />
    </relation>
    <relation id="5" arity="3" name="arrow_connection">
      <symbolView symbolDataRef="17" />
      <symbolView symbolDataRef="20" connectionPoint="right" />
      <symbolView symbolDataRef="24" connectionPoint="top" />
    </relation>
    <relation id="6" arity="3" name="arrow_connection">
      <symbolView symbolDataRef="18" />
      <symbolView symbolDataRef="21" connectionPoint="right" />
      <symbolView symbolDataRef="24" connectionPoint="left" />
    </relation>
    <relation id="7" arity="2" name="text_inside">
      <symbolView symbolDataRef="0" />
      <symbolView symbolDataRef="22" />
    </relation>
    <relation id="8" arity="2" name="arrow_label">
      <symbolView symbolDataRef="1" />
      <symbolView symbolDataRef="13" />
    </relation>
    <relation id="9" arity="2" name="text_inside">
      <symbolView symbolDataRef="2" />
      <symbolView symbolDataRef="19" />
    </relation>
    <relation id="10" arity="2" name="arrow_label">
      <symbolView symbolDataRef="3" />
      <symbolView symbolDataRef="14" />
    </relation>
    <relation id="11" arity="2" name="text_inside">
      <symbolView symbolDataRef="4" />
      <symbolView symbolDataRef="23" />
    </relation>
    <relation id="12" arity="2" name="text_inside">
      <symbolView symbolDataRef="5" />
      <symbolView symbolDataRef="20" />
    </relation>
    <relation id="13" arity="2" name="arrow_label">
      <symbolView symbolDataRef="6" />
      <symbolView symbolDataRef="16" />
    </relation>
    <relation id="14" arity="2" name="arrow_label">
      <symbolView symbolDataRef="7" />
      <symbolView symbolDataRef="17" />
    </relation>
    <relation id="15" arity="2" name="arrow_label">
      <symbolView symbolDataRef="8" />
      <symbolView symbolDataRef="15" />
    </relation>
    <relation id="16" arity="2" name="text_inside">
      <symbolView symbolDataRef="9" />
      <symbolView symbolDataRef="21" />
    </relation>
    <relation id="17" arity="2" name="arrow_label">
      <symbolView symbolDataRef="10" />
      <symbolView symbolDataRef="18" />
    </relation>
    <relation id="18" arity="2" name="text_inside">
      <symbolView symbolDataRef="11" />
      <symbolView symbolDataRef="24" />
    </relation>
  </relations>
</offlineAnnotation>