<?xml version="1.0" encoding="utf-8"?>
<offlineAnnotation>
  <registration>
    <markers>
      <point x="169" y="4" />
      <point x="2747" y="2002" />
    </markers>
    <frameOffset>5</frameOffset>
    <scale>0.0983233592165785</scale>
    <translation>174 9</translation>
    <rotation>0 174 9</rotation>
  </registration>
  <symbols>
    <symbol id="0" name="text">
      <bounds x="1115" y="59" width="239" height="62" />
      <textMeaning>Start</textMeaning>
    </symbol>
    <symbol id="1" name="text">
      <bounds x="1072" y="372" width="485" height="169" />
      <textMeaning>Do I want\\to do this?</textMeaning>
    </symbol>
    <symbol id="2" name="text">
      <bounds x="1446" y="719" width="78" height="72" />
      <textMeaning>No</textMeaning>
    </symbol>
    <symbol id="3" name="text">
      <bounds x="2525" y="820" width="127" height="89" />
      <textMeaning>Yes</textMeaning>
    </symbol>
    <symbol id="4" name="text">
      <bounds x="1087" y="998" width="646" height="153" />
      <textMeaning>Will it likely\\end in disaster?</textMeaning>
    </symbol>
    <symbol id="5" name="text">
      <bounds x="214" y="1488" width="430" height="89" />
      <textMeaning>Don't do it.</textMeaning>
    </symbol>
    <symbol id="6" name="text">
      <bounds x="1495" y="1336" width="122" height="75" />
      <textMeaning>Yes</textMeaning>
    </symbol>
    <symbol id="7" name="text">
      <bounds x="2097" y="1232" width="101" height="62" />
      <textMeaning>Yes</textMeaning>
    </symbol>
    <symbol id="8" name="text">
      <bounds x="2325" y="1382" width="325" height="107" />
      <textMeaning>Do it!</textMeaning>
    </symbol>
    <symbol id="9" name="text">
      <bounds x="637" y="1800" width="75" height="64" />
      <textMeaning>No</textMeaning>
    </symbol>
    <symbol id="10" name="text">
      <bounds x="1064" y="1666" width="755" height="184" />
      <textMeaning>Will it make a good\\story anyway?</textMeaning>
    </symbol>
    <symbol id="11" name="text">
      <bounds x="2041" y="1615" width="136" height="74" />
      <textMeaning>Yes</textMeaning>
    </symbol>
    <symbol id="12" name="arrow">
      <bounds x="1219" y="178" width="45" height="113" />
      <arrowAnnotation>
        <headBounds x="1219" y="224" width="45" height="66" />
        <from x="1241" y="178" />
        <to x="1249" y="290" />
      </arrowAnnotation>
    </symbol>
    <symbol id="13" name="arrow">
      <bounds x="1353" y="744" width="55" height="121" />
      <arrowAnnotation>
        <headBounds x="1353" y="795" width="55" height="70" />
        <from x="1362" y="744" />
        <to x="1388" y="865" />
      </arrowAnnotation>
    </symbol>
    <symbol id="14" name="arrow">
      <bounds x="1737" y="447" width="791" height="902" />
      <arrowAnnotation>
        <headBounds x="2484" y="1241" width="43" height="107" />
        <from x="1737" y="457" />
        <to x="2526" y="1348" />
      </arrowAnnotation>
    </symbol>
    <symbol id="15" name="arrow">
      <bounds x="1451" y="1327" width="46" height="160" />
      <arrowAnnotation>
        <headBounds x="1451" y="1422" width="46" height="65" />
        <from x="1459" y="1327" />
        <to x="1480" y="1486" />
      </arrowAnnotation>
    </symbol>
    <symbol id="16" name="arrow">
      <bounds x="1877" y="1069" width="404" height="371" />
      <arrowAnnotation>
        <headBounds x="2235" y="1415" width="46" height="25" />
        <from x="1877" y="1084" />
        <to x="2281" y="1427" />
      </arrowAnnotation>
    </symbol>
    <symbol id="17" name="arrow">
      <bounds x="390" y="1632" width="502" height="142" />
      <arrowAnnotation>
        <headBounds x="390" y="1632" width="69" height="49" />
        <from x="891" y="1753" />
        <to x="414" y="1632" />
      </arrowAnnotation>
    </symbol>
    <symbol id="18" name="arrow">
      <bounds x="1996" y="1553" width="602" height="178" />
      <arrowAnnotation>
        <headBounds x="2512" y="1553" width="86" height="49" />
        <from x="1996" y="1729" />
        <to x="2536" y="1553" />
      </arrowAnnotation>
    </symbol>
    <symbol id="19" name="decision">
      <bounds x="838" y="271" width="886" height="462" />
    </symbol>
    <symbol id="20" name="decision">
      <bounds x="861" y="846" width="1022" height="462" />
    </symbol>
    <symbol id="21" name="decision">
      <bounds x="887" y="1471" width="1094" height="527" />
    </symbol>
    <symbol id="22" name="terminator">
      <bounds x="1044" y="9" width="361" height="178" />
    </symbol>
    <symbol id="23" name="terminator">
      <bounds x="174" y="1409" width="539" height="226" />
    </symbol>
    <symbol id="24" name="terminator">
      <bounds x="2278" y="1343" width="464" height="217" />
    </symbol>
  </symbols>
  <relations>
    <relation id="0" arity="3" name="arrow_connection">
      <symbolView symbolDataRef="12" />
      <symbolView symbolDataRef="22" connectionPoint="bottom" />
      <symbolView symbolDataRef="19" connectionPoint="top" />
    </relation>
    <relation id="1" arity="3" name="arrow_connection">
      <symbolView symbolDataRef="13" />
      <symbolView symbolDataRef="19" connectionPoint="bottom" />
      <symbolView symbolDataRef="20" connectionPoint="top" />
    </relation>
    <relation id="2" arity="3" name="arrow_connection">
      <symbolView symbolDataRef="14" />
      <symbolView symbolDataRef="19" connectionPoint="right" />
      <symbolView symbolDataRef="24" connectionPoint="top" />
    </relation>
    <relation id="3" arity="3" name="arrow_connection">
      <symbolView symbolDataRef="15" />
      <symbolView symbolDataRef="20" connectionPoint="bottom" />
      <symbolView symbolDataRef="21" connectionPoint="top" />
    </relation>
    <relation id="4" arity="3" name="arrow_connection">
      <symbolView symbolDataRef="16" />
      <symbolView symbolDataRef="20" connectionPoint="right" />
      <symbolView symbolDataRef="24" connectionPoint="left" />
    </relation>
    <relation id="5" arity="3" name="arrow_connection">
      <symbolView symbolDataRef="17" />
      <symbolView symbolDataRef="21" connectionPoint="left" />
      <symbolView symbolDataRef="23" connectionPoint="bottom" />
    </relation>
    <relation id="6" arity="3" name="arrow_connection">
      <symbolView symbolDataRef="18" />
      <symbolView symbolDataRef="21" connectionPoint="right" />
      <symbolView symbolDataRef="24" connectionPoint="bottom" />
    </relation>
    <relation id="7" arity="2" name="text_inside">
      <symbolView symbolDataRef="0" />
      <symbolView symbolDataRef="22" />
    </relation>
    <relation id="8" arity="2" name="text_inside">
      <symbolView symbolDataRef="1" />
      <symbolView symbolDataRef="19" />
    </relation>
    <relation id="9" arity="2" name="arrow_label">
      <symbolView symbolDataRef="2" />
      <symbolView symbolDataRef="13" />
    </relation>
    <relation id="10" arity="2" name="arrow_label">
      <symbolView symbolDataRef="3" />
      <symbolView symbolDataRef="14" />
    </relation>
    <relation id="11" arity="2" name="text_inside">
      <symbolView symbolDataRef="4" />
      <symbolView symbolDataRef="20" />
    </relation>
    <relation id="12" arity="2" name="text_inside">
      <symbolView symbolDataRef="5" />
      <symbolView symbolDataRef="23" />
    </relation>
    <relation id="13" arity="2" name="arrow_label">
      <symbolView symbolDataRef="6" />
      <symbolView symbolDataRef="15" />
    </relation>
    <relation id="14" arity="2" name="arrow_label">
      <symbolView symbolDataRef="7" />
      <symbolView symbolDataRef="16" />
    </relation>
    <relation id="15" arity="2" name="text_inside">
      <symbolView symbolDataRef="8" />
      <symbolView symbolDataRef="24" />
    </relation>
    <relation id="16" arity="2" name="arrow_label">
      <symbolView symbolDataRef="9" />
      <symbolView symbolDataRef="17" />
    </relation>
    <relation id="17" arity="2" name="text_inside">
      <symbolView symbolDataRef="10" />
      <symbolView symbolDataRef="21" />
    </relation>
    <relation id="18" arity="2" name="arrow_label">
      <symbolView symbolDataRef="11" />
      <symbolView symbolDataRef="18" />
    </relation>
  </relations>
</offlineAnnotation>